ttsign_mobile/__init__.py
ttsign_mobile/ttsign_mobile.py
ttsign_mobile-1.0.0.dist-info/licenses/LICENSE
ttsign_mobile-1.0.0.dist-info/METADATA
ttsign_mobile-1.0.0.dist-info/WHEEL
ttsign_mobile-1.0.0.dist-info/top_level.txt
ttsign_mobile-1.0.0.dist-info/RECORD
