Metadata-Version: 2.4
Name: ttsign-mobile
Version: 1.0.0
Summary: Python library for generating TikTok mobile API signatures
Home-page: https://github.com/djoub/ttsign-mobile
Author: djoub
Author-email: djoub <benchehba@gmail.com>
License: MIT
Project-URL: Homepage, https://github.com/djoub/ttsign-mobile
Project-URL: Bug Tracker, https://github.com/djoub/ttsign-mobile/issues
Keywords: tiktok,api,signature,mobile,gorgon
Classifier: Development Status :: 4 - Beta
Classifier: Intended Audience :: Developers
Classifier: License :: OSI Approved :: MIT License
Classifier: Programming Language :: Python :: 3
Classifier: Programming Language :: Python :: 3.6
Classifier: Programming Language :: Python :: 3.7
Classifier: Programming Language :: Python :: 3.8
Classifier: Programming Language :: Python :: 3.9
Classifier: Programming Language :: Python :: 3.10
Classifier: Programming Language :: Python :: 3.11
Classifier: Operating System :: OS Independent
Classifier: Topic :: Software Development :: Libraries :: Python Modules
Requires-Python: >=3.6
License-File: LICENSE
Dynamic: author
Dynamic: home-page
Dynamic: license-file
Dynamic: requires-python
